base.py
bot.py
connectm.py
fakes.py
gui.py
tui.py
connectm-1.1.0.dist-info/LICENSE
connectm-1.1.0.dist-info/METADATA
connectm-1.1.0.dist-info/WHEEL
connectm-1.1.0.dist-info/entry_points.txt
connectm-1.1.0.dist-info/top_level.txt
connectm-1.1.0.dist-info/RECORD
