Metadata-Version: 2.1
Name: connectm
Version: 1.1.0
Summary: Connect-M
Author-email: University of Chicago - Department of Computer Science <borja@cs.uchicago.edu>
Project-URL: Homepage, https://github.com/uchicago-cs/connectm
Project-URL: Bug Tracker, https://github.com/uchicago-cs/connectm/issues
Classifier: Programming Language :: Python :: 3
Classifier: License :: OSI Approved :: BSD License
Classifier: Operating System :: OS Independent
Requires-Python: >=3.10
License-File: LICENSE
Requires-Dist: click >=8.1.7
Requires-Dist: colorama >=0.4.6
Requires-Dist: mypy >=1.7.1
Requires-Dist: mypy-extensions >=1.0.0
Requires-Dist: pygame >=2.5.2
Requires-Dist: pytest >=7.4.3
Requires-Dist: types-colorama >=0.4.15.12
